testver/__init__.py
testver/__main__.py
testver-0.3.1.dist-info/entry_points.txt
testver-0.3.1.dist-info/LICENSE
testver-0.3.1.dist-info/WHEEL
testver-0.3.1.dist-info/METADATA
testver-0.3.1.dist-info/RECORD
