Metadata-Version: 2.1
Name: testver
Version: 0.3.1
Summary: Programmatically edit python package versions for testing.
Home-page: https://www.github.com/janfreyberg/testver
Author: Jan Freyberg
Author-email: jan.freyberg@gmail.com
Classifier: License :: OSI Approved :: MIT License
Requires-Dist: astunparse
